vendi_score/__init__.py
vendi_score/data_utils.py
vendi_score/image_utils.py
vendi_score/inception.py
vendi_score/molecule_utils.py
vendi_score/notebook_utils.py
vendi_score/text_utils.py
vendi_score/vendi.py
vendi_score-0.0.1.dist-info/LICENSE
vendi_score-0.0.1.dist-info/METADATA
vendi_score-0.0.1.dist-info/WHEEL
vendi_score-0.0.1.dist-info/top_level.txt
vendi_score-0.0.1.dist-info/RECORD
