Metadata-Version: 2.1
Name: vendi-score
Version: 0.0.1
Summary: A diversity metric for machine learning
Author-email: Dan Friedman <dfriedman@princeton.edu>
License: MIT
Project-URL: Documentation, https://github.com/vertaix/Vendi-Score
Project-URL: Issues, https://github.com/vertaix/Vendi-Score/issues
Project-URL: Source, https://github.com/vertaix/Vendi-Score
Classifier: Programming Language :: Python :: 3
Requires-Python: >=3.7
License-File: LICENSE
Requires-Dist: numpy (>=1.14)
Requires-Dist: scipy (>=1.3.2)
Requires-Dist: scikit-learn (>=1.1)
Provides-Extra: all
Requires-Dist: torch ; extra == 'all'
Requires-Dist: torchvision ; extra == 'all'
Requires-Dist: transformers ; extra == 'all'
Requires-Dist: datasets ; extra == 'all'
Requires-Dist: nltk ; extra == 'all'
Requires-Dist: rdkit ; extra == 'all'
Provides-Extra: images
Requires-Dist: torch ; extra == 'images'
Requires-Dist: torchvision ; extra == 'images'
Provides-Extra: molecules
Requires-Dist: rdkit ; extra == 'molecules'
Provides-Extra: text
Requires-Dist: torch ; extra == 'text'
Requires-Dist: transformers ; extra == 'text'
Requires-Dist: datasets ; extra == 'text'
Requires-Dist: nltk ; extra == 'text'
